[
  {
    "id": "tide-2026-02-05T02:59:00.000Z",
    "summary": "Low Tide 1.7 m",
    "start": "2026-02-05T02:59:00.000Z",
    "end": "2026-02-05T03:00:00.000Z",
    "description": "Height: 1.6970757010054154 m",
    "location": "St Helier, Jersey",
    "timezone": "Europe/Jersey"
  },
  {
    "id": "tide-2026-02-05T08:36:00.000Z",
    "summary": "High Tide 10.9 m",
    "start": "2026-02-05T08:36:00.000Z",
    "end": "2026-02-05T08:37:00.000Z",
    "description": "Height: 10.898416472377502 m",
    "location": "St Helier, Jersey",
    "timezone": "Europe/Jersey"
  },
  {
    "id": "tide-2026-02-05T15:17:00.000Z",
    "summary": "Low Tide 1.7 m",
    "start": "2026-02-05T15:17:00.000Z",
    "end": "2026-02-05T15:18:00.000Z",
    "description": "Height: 1.6726162798903905 m",
    "location": "St Helier, Jersey",
    "timezone": "Europe/Jersey"
  },
  {
    "id": "tide-2026-02-05T20:55:00.000Z",
    "summary": "High Tide 10.5 m",
    "start": "2026-02-05T20:55:00.000Z",
    "end": "2026-02-05T20:56:00.000Z",
    "description": "Height: 10.473733432411063 m",
    "location": "St Helier, Jersey",
    "timezone": "Europe/Jersey"
  },
  {
    "id": "tide-2026-02-06T03:29:00.000Z",
    "summary": "Low Tide 2.0 m",
    "start": "2026-02-06T03:29:00.000Z",
    "end": "2026-02-06T03:30:00.000Z",
    "description": "Height: 2.0481120527048873 m",
    "location": "St Helier, Jersey",
    "timezone": "Europe/Jersey"
  },
  {
    "id": "tide-2026-02-06T09:10:00.000Z",
    "summary": "High Tide 10.5 m",
    "start": "2026-02-06T09:10:00.000Z",
    "end": "2026-02-06T09:11:00.000Z",
    "description": "Height: 10.464195360571523 m",
    "location": "St Helier, Jersey",
    "timezone": "Europe/Jersey"
  },
  {
    "id": "tide-2026-02-06T15:46:00.000Z",
    "summary": "Low Tide 2.1 m",
    "start": "2026-02-06T15:46:00.000Z",
    "end": "2026-02-06T15:47:00.000Z",
    "description": "Height: 2.148847173050247 m",
    "location": "St Helier, Jersey",
    "timezone": "Europe/Jersey"
  },
  {
    "id": "tide-2026-02-06T21:28:00.000Z",
    "summary": "High Tide 10.0 m",
    "start": "2026-02-06T21:28:00.000Z",
    "end": "2026-02-06T21:29:00.000Z",
    "description": "Height: 10.008369510523298 m",
    "location": "St Helier, Jersey",
    "timezone": "Europe/Jersey"
  }
]