[
  {
    "height": -2.5335716976240485,
    "time": "2026-04-08T03:48:00+00:00",
    "type": "low"
  },
  {
    "height": 2.699315006375082,
    "time": "2026-04-08T09:41:00+00:00",
    "type": "high"
  },
  {
    "height": -2.13318431569077,
    "time": "2026-04-08T16:03:00+00:00",
    "type": "low"
  },
  {
    "height": 2.5213704638942063,
    "time": "2026-04-08T21:58:00+00:00",
    "type": "high"
  },
  {
    "height": -1.947971685072607,
    "time": "2026-04-09T04:33:00+00:00",
    "type": "low"
  },
  {
    "height": 2.0019225903844555,
    "time": "2026-04-09T10:21:00+00:00",
    "type": "high"
  },
  {
    "height": -1.5274163562528105,
    "time": "2026-04-09T16:57:00+00:00",
    "type": "low"
  },
  {
    "height": 1.8306395065339687,
    "time": "2026-04-09T22:44:00+00:00",
    "type": "high"
  }
]