[
  {
    "id": "tide-2026-08-20T23:02:00.000Z",
    "summary": "High Tide 8.0 m",
    "start": "2026-08-21T00:02:00.000Z",
    "end": "2026-08-21T00:03:00.000Z",
    "description": "Height: 7.977494457512695 m",
    "location": "St Helier, Jersey",
    "timezone": "Europe/Jersey"
  },
  {
    "id": "tide-2026-08-21T05:37:00.000Z",
    "summary": "Low Tide 4.3 m",
    "start": "2026-08-21T06:37:00.000Z",
    "end": "2026-08-21T06:38:00.000Z",
    "description": "Height: 4.252507434175438 m",
    "location": "St Helier, Jersey",
    "timezone": "Europe/Jersey"
  },
  {
    "id": "tide-2026-08-21T11:25:00.000Z",
    "summary": "High Tide 7.8 m",
    "start": "2026-08-21T12:25:00.000Z",
    "end": "2026-08-21T12:26:00.000Z",
    "description": "Height: 7.769491281507267 m",
    "location": "St Helier, Jersey",
    "timezone": "Europe/Jersey"
  },
  {
    "id": "tide-2026-08-21T18:08:00.000Z",
    "summary": "Low Tide 4.6 m",
    "start": "2026-08-21T19:08:00.000Z",
    "end": "2026-08-21T19:09:00.000Z",
    "description": "Height: 4.623436420002578 m",
    "location": "St Helier, Jersey",
    "timezone": "Europe/Jersey"
  },
  {
    "id": "tide-2026-08-22T00:10:00.000Z",
    "summary": "High Tide 7.3 m",
    "start": "2026-08-22T01:10:00.000Z",
    "end": "2026-08-22T01:11:00.000Z",
    "description": "Height: 7.28466195136222 m",
    "location": "St Helier, Jersey",
    "timezone": "Europe/Jersey"
  },
  {
    "id": "tide-2026-08-22T06:43:00.000Z",
    "summary": "Low Tide 4.8 m",
    "start": "2026-08-22T07:43:00.000Z",
    "end": "2026-08-22T07:44:00.000Z",
    "description": "Height: 4.806673083613397 m",
    "location": "St Helier, Jersey",
    "timezone": "Europe/Jersey"
  },
  {
    "id": "tide-2026-08-22T13:02:00.000Z",
    "summary": "High Tide 7.3 m",
    "start": "2026-08-22T14:02:00.000Z",
    "end": "2026-08-22T14:03:00.000Z",
    "description": "Height: 7.302708533731136 m",
    "location": "St Helier, Jersey",
    "timezone": "Europe/Jersey"
  },
  {
    "id": "tide-2026-08-22T19:47:00.000Z",
    "summary": "Low Tide 4.9 m",
    "start": "2026-08-22T20:47:00.000Z",
    "end": "2026-08-22T20:48:00.000Z",
    "description": "Height: 4.941649499267804 m",
    "location": "St Helier, Jersey",
    "timezone": "Europe/Jersey"
  }
]