[
  {
    "height": -3.357532476038131,
    "time": "2026-08-05T04:37:00+00:00",
    "type": "low"
  },
  {
    "height": 3.377090975282635,
    "time": "2026-08-05T10:18:00+00:00",
    "type": "high"
  },
  {
    "height": -3.0610536819489136,
    "time": "2026-08-05T16:55:00+00:00",
    "type": "low"
  },
  {
    "height": 3.325066575006278,
    "time": "2026-08-05T22:36:00+00:00",
    "type": "high"
  },
  {
    "height": -2.8787263624245045,
    "time": "2026-08-06T05:17:00+00:00",
    "type": "low"
  },
  {
    "height": 2.932941761486912,
    "time": "2026-08-06T11:03:00+00:00",
    "type": "high"
  },
  {
    "height": -2.5951876841778003,
    "time": "2026-08-06T17:43:00+00:00",
    "type": "low"
  }
]