[
  {
    "id": "tide-2025-12-24T03:18:00.000Z",
    "summary": "Low Tide 2.7 m",
    "start": "2025-12-24T03:18:00.000Z",
    "end": "2025-12-24T03:19:00.000Z",
    "description": "Height: 2.709792636068403 m",
    "location": "St Helier, Jersey",
    "timezone": "Europe/Jersey"
  },
  {
    "id": "tide-2025-12-24T08:52:00.000Z",
    "summary": "High Tide 10.0 m",
    "start": "2025-12-24T08:52:00.000Z",
    "end": "2025-12-24T08:53:00.000Z",
    "description": "Height: 10.040209761435317 m",
    "location": "St Helier, Jersey",
    "timezone": "Europe/Jersey"
  },
  {
    "id": "tide-2025-12-24T15:42:00.000Z",
    "summary": "Low Tide 2.5 m",
    "start": "2025-12-24T15:42:00.000Z",
    "end": "2025-12-24T15:43:00.000Z",
    "description": "Height: 2.4684492777205533 m",
    "location": "St Helier, Jersey",
    "timezone": "Europe/Jersey"
  },
  {
    "id": "tide-2025-12-24T21:15:00.000Z",
    "summary": "High Tide 9.8 m",
    "start": "2025-12-24T21:15:00.000Z",
    "end": "2025-12-24T21:16:00.000Z",
    "description": "Height: 9.750071499963463 m",
    "location": "St Helier, Jersey",
    "timezone": "Europe/Jersey"
  },
  {
    "id": "tide-2025-12-25T03:58:00.000Z",
    "summary": "Low Tide 2.8 m",
    "start": "2025-12-25T03:58:00.000Z",
    "end": "2025-12-25T03:59:00.000Z",
    "description": "Height: 2.816088084096428 m",
    "location": "St Helier, Jersey",
    "timezone": "Europe/Jersey"
  },
  {
    "id": "tide-2025-12-25T09:33:00.000Z",
    "summary": "High Tide 9.9 m",
    "start": "2025-12-25T09:33:00.000Z",
    "end": "2025-12-25T09:34:00.000Z",
    "description": "Height: 9.903455003866647 m",
    "location": "St Helier, Jersey",
    "timezone": "Europe/Jersey"
  },
  {
    "id": "tide-2025-12-25T16:23:00.000Z",
    "summary": "Low Tide 2.6 m",
    "start": "2025-12-25T16:23:00.000Z",
    "end": "2025-12-25T16:24:00.000Z",
    "description": "Height: 2.6018031748871087 m",
    "location": "St Helier, Jersey",
    "timezone": "Europe/Jersey"
  },
  {
    "id": "tide-2025-12-25T21:58:00.000Z",
    "summary": "High Tide 9.6 m",
    "start": "2025-12-25T21:58:00.000Z",
    "end": "2025-12-25T21:59:00.000Z",
    "description": "Height: 9.553900396150507 m",
    "location": "St Helier, Jersey",
    "timezone": "Europe/Jersey"
  }
]