[
  {
    "height": -2.7183537694504607,
    "time": "2026-01-10T05:14:00+00:00",
    "type": "low"
  },
  {
    "height": 2.8918575901041605,
    "time": "2026-01-10T11:02:00+00:00",
    "type": "high"
  },
  {
    "height": -2.5958661147017126,
    "time": "2026-01-10T17:37:00+00:00",
    "type": "low"
  },
  {
    "height": 2.4243830155527593,
    "time": "2026-01-10T23:27:00+00:00",
    "type": "high"
  },
  {
    "height": -2.2256529141780677,
    "time": "2026-01-11T05:54:00+00:00",
    "type": "low"
  },
  {
    "height": 2.254417052655405,
    "time": "2026-01-11T11:50:00+00:00",
    "type": "high"
  },
  {
    "height": -2.0841582683624744,
    "time": "2026-01-11T18:19:00+00:00",
    "type": "low"
  }
]