[
  {
    "id": "tide-2026-05-15T23:52:00.000Z",
    "summary": "Low Tide 1.7 m",
    "start": "2026-05-16T00:52:00.000Z",
    "end": "2026-05-16T00:53:00.000Z",
    "description": "Height: 1.7044959246944371 m",
    "location": "St Helier, Jersey",
    "timezone": "Europe/Jersey"
  },
  {
    "id": "tide-2026-05-16T05:40:00.000Z",
    "summary": "High Tide 10.9 m",
    "start": "2026-05-16T06:40:00.000Z",
    "end": "2026-05-16T06:41:00.000Z",
    "description": "Height: 10.897652173915557 m",
    "location": "St Helier, Jersey",
    "timezone": "Europe/Jersey"
  },
  {
    "id": "tide-2026-05-16T12:16:00.000Z",
    "summary": "Low Tide 1.5 m",
    "start": "2026-05-16T13:16:00.000Z",
    "end": "2026-05-16T13:17:00.000Z",
    "description": "Height: 1.492878788744246 m",
    "location": "St Helier, Jersey",
    "timezone": "Europe/Jersey"
  },
  {
    "id": "tide-2026-05-16T18:03:00.000Z",
    "summary": "High Tide 11.1 m",
    "start": "2026-05-16T19:03:00.000Z",
    "end": "2026-05-16T19:04:00.000Z",
    "description": "Height: 11.082105808486 m",
    "location": "St Helier, Jersey",
    "timezone": "Europe/Jersey"
  },
  {
    "id": "tide-2026-05-17T00:42:00.000Z",
    "summary": "Low Tide 1.3 m",
    "start": "2026-05-17T01:42:00.000Z",
    "end": "2026-05-17T01:43:00.000Z",
    "description": "Height: 1.3392202338226644 m",
    "location": "St Helier, Jersey",
    "timezone": "Europe/Jersey"
  },
  {
    "id": "tide-2026-05-17T06:27:00.000Z",
    "summary": "High Tide 11.2 m",
    "start": "2026-05-17T07:27:00.000Z",
    "end": "2026-05-17T07:28:00.000Z",
    "description": "Height: 11.161391624910983 m",
    "location": "St Helier, Jersey",
    "timezone": "Europe/Jersey"
  },
  {
    "id": "tide-2026-05-17T13:05:00.000Z",
    "summary": "Low Tide 1.3 m",
    "start": "2026-05-17T14:05:00.000Z",
    "end": "2026-05-17T14:06:00.000Z",
    "description": "Height: 1.3416507750897813 m",
    "location": "St Helier, Jersey",
    "timezone": "Europe/Jersey"
  },
  {
    "id": "tide-2026-05-17T18:49:00.000Z",
    "summary": "High Tide 11.3 m",
    "start": "2026-05-17T19:49:00.000Z",
    "end": "2026-05-17T19:50:00.000Z",
    "description": "Height: 11.287951550016263 m",
    "location": "St Helier, Jersey",
    "timezone": "Europe/Jersey"
  }
]